comfyui_siberianodes-1.0.0.dist-info/licenses/LICENSE
llm/__init__.py
llm/chat_node.py
llm/connector.py
llm/endpoints.py
llm/ollama_sdk_client.py
llm/vision_node.py
utils/__init__.py
utils/display_node.py
utils/utils.py
web/__init__.py
web/js/siberiaDisplay.js
web/js/siberiaOllama.js
comfyui_siberianodes-1.0.0.dist-info/METADATA
comfyui_siberianodes-1.0.0.dist-info/WHEEL
comfyui_siberianodes-1.0.0.dist-info/top_level.txt
comfyui_siberianodes-1.0.0.dist-info/RECORD
