Metadata-Version: 2.4
Name: comfyui-siberianodes
Version: 1.0.0
Summary: Custom nodes for ComfyUI with Ollama integration for LLM chat, vision analysis, and utilities
Author-email: siberiah0h <siberiah0h@gmail.com>
Maintainer-email: siberiah0h <siberiah0h@gmail.com>
License: MIT
Project-URL: Repository, https://github.com/siberiah2o/ComfyUI-SiberiaNodes
Project-URL: Documentation, https://github.com/siberiah2o/ComfyUI-SiberiaNodes/blob/main/README.md
Project-URL: Bug Reports, https://github.com/siberiah2o/ComfyUI-SiberiaNodes/issues
Project-URL: Source Code, https://github.com/siberiah2o/ComfyUI-SiberiaNodes
Project-URL: Technical Blog, https://www.dataeast.cn
Keywords: comfyui,custom-nodes,ollama,llm,ai,image-analysis,chat,siberia
Classifier: Development Status :: 4 - Beta
Classifier: Intended Audience :: Developers
Classifier: Intended Audience :: Science/Research
Classifier: License :: OSI Approved :: MIT License
Classifier: Operating System :: OS Independent
Classifier: Programming Language :: Python :: 3
Classifier: Programming Language :: Python :: 3.8
Classifier: Programming Language :: Python :: 3.9
Classifier: Programming Language :: Python :: 3.10
Classifier: Programming Language :: Python :: 3.11
Classifier: Programming Language :: Python :: 3.12
Classifier: Topic :: Scientific/Engineering :: Artificial Intelligence
Classifier: Topic :: Multimedia :: Graphics
Requires-Python: >=3.8
License-File: LICENSE
Requires-Dist: torch>=1.13.0
Requires-Dist: numpy>=1.21.0
Requires-Dist: Pillow>=8.0.0
Requires-Dist: typing-extensions>=4.0.0
Requires-Dist: requests>=2.25.0
Requires-Dist: ollama>=0.1.0
Dynamic: license-file
